{"stat.useItem.minecraft.string":46,"stat.beaconInteraction":16,"stat.useItem.minecraft.bow":65,"stat.drop.minecraft.mutton":2,"stat.drop.minecraft.armor_stand":1,"stat.useItem.minecraft.painting":46,"stat.useItem.minecraft.quartz_block":2699,"stat.pickup.minecraft.wooden_slab":14,"stat.leaveGame":534,"stat.drop.minecraft.gunpowder":52,"stat.useItem.minecraft.bookshelf":172,"stat.craftItem.minecraft.iron_axe":4,"stat.drop.minecraft.redstone":32,"stat.useItem.minecraft.glowstone":131,"stat.mineBlock.minecraft.sandstone":2,"stat.drop.minecraft.shield":3,"stat.useItem.minecraft.mutton":2,"stat.drop.minecraft.trapdoor":3,"stat.drop.minecraft.skull":1,"stat.craftItem.minecraft.shield":2,"stat.useItem.minecraft.planks":7296,"stat.pickup.minecraft.glowstone_dust":2,"stat.useItem.minecraft.fire_charge":2,"stat.pickup.minecraft.porkchop":67,"stat.pickup.minecraft.glass":39,"stat.drop.minecraft.iron_sword":3,"stat.useItem.minecraft.water_bucket":99,"stat.pickup.minecraft.rotten_flesh":63,"stat.drop.minecraft.redstone_torch":1,"stat.useItem.minecraft.diamond_hoe":3,"stat.pickup.minecraft.sand":332,"stat.pickup.minecraft.splash_potion":4,"stat.useItem.minecraft.activator_rail":1,"stat.killEntity.Donkey":2,"stat.pickup.minecraft.name_tag":3,"stat.pickup.minecraft.bucket":4,"stat.useItem.minecraft.rail":68,"stat.killEntity.Enderman":6,"stat.drop.minecraft.splash_potion":7,"stat.mineBlock.minecraft.wooden_slab":14,"stat.aviateOneCm":1149428,"stat.useItem.minecraft.anvil":4,"stat.pickup.minecraft.brown_mushroom":8,"stat.mineBlock.minecraft.sand":227,"stat.killEntity.Witch":2,"stat.drop.minecraft.sand":129,"stat.pickup.minecraft.mob_spawner":2,"stat.drop.minecraft.tnt":1,"stat.hopperInspected":103,"stat.useItem.minecraft.iron_pickaxe":688,"stat.drop.minecraft.diamond":20,"stat.useItem.minecraft.spawn_egg":75,"stat.pickup.minecraft.stained_hardened_clay":2,"stat.craftItem.minecraft.wooden_pickaxe":3,"stat.pickup.minecraft.packed_ice":1,"stat.drop.minecraft.cooked_mutton":13,"stat.pickup.minecraft.double_plant":28,"stat.craftItem.minecraft.bed":5,"stat.trappedChestTriggered":13,"stat.craftItem.minecraft.glass_pane":16,"stat.mineBlock.minecraft.hopper":4,"stat.mineBlock.minecraft.vine":5,"stat.useItem.minecraft.oak_stairs":1193,"stat.craftItem.minecraft.golden_carrot":1,"stat.drop.minecraft.gravel":17,"stat.furnaceInteraction":219,"stat.drop.minecraft.diamond_block":15,"stat.useItem.minecraft.pumpkin_seeds":4,"stat.killEntity.ZombieVillager":2,"stat.useItem.minecraft.dark_oak_stairs":56,"stat.pickup.minecraft.wooden_button":5,"stat.drop.minecraft.purple_shulker_box":1,"stat.drop.minecraft.red_flower":2,"stat.useItem.minecraft.minecart":20,"stat.pickup.minecraft.beef":47,"stat.useItem.minecraft.cooked_mutton":38,"stat.pickup.minecraft.furnace":2,"stat.useItem.minecraft.redstone":1651,"stat.drop.minecraft.stained_hardened_clay":1,"stat.pickup.minecraft.cauldron":2,"stat.mineBlock.minecraft.stained_hardened_clay":16,"stat.useItem.minecraft.trapdoor":210,"stat.pickup.minecraft.cyan_shulker_box":37,"stat.useItem.minecraft.stained_glass":6,"stat.pickup.minecraft.iron_chestplate":5,"stat.useItem.minecraft.fence":126,"stat.pickup.minecraft.skull":1,"stat.useItem.minecraft.dark_oak_door":15,"stat.killEntity.Horse":10,"stat.pickup.minecraft.potion":1,"stat.useItem.minecraft.cauldron":12,"stat.useItem.minecraft.flint_and_steel":63,"stat.mineBlock.minecraft.fence":10,"stat.useItem.minecraft.wheat_seeds":21,"stat.mineBlock.minecraft.sea_lantern":1,"stat.useItem.minecraft.wooden_button":10,"stat.killEntity.Husk":1,"stat.drop.minecraft.iron_horse_armor":3,"stat.useItem.minecraft.hopper":119,"stat.pickup.minecraft.saddle":4,"stat.useItem.minecraft.dye":57,"stat.useItem.minecraft.beef":1,"stat.mineBlock.minecraft.oak_stairs":155,"stat.pickup.minecraft.lever":1,"stat.deaths":125,"stat.playOneMinute":7744246,"stat.pickup.minecraft.birch_door":2,"stat.mineBlock.minecraft.stone_pressure_plate":3,"stat.craftItem.minecraft.iron_pickaxe":1,"stat.pickup.minecraft.glass_pane":8,"stat.pickup.minecraft.sea_lantern":1,"stat.drop.minecraft.chest":7,"stat.drop.minecraft.iron_ingot":26,"stat.drop.minecraft.torch":1,"stat.useItem.minecraft.jukebox":3,"stat.mineBlock.minecraft.tallgrass":441,"stat.craftItem.minecraft.cooked_mutton":56,"stat.pickup.minecraft.cooked_mutton":24,"stat.chestOpened":421,"stat.useItem.minecraft.splash_potion":20,"stat.pickup.minecraft.pumpkin":1,"stat.recordPlayed":1,"stat.useItem.minecraft.stone":2220,"stat.drop.minecraft.detector_rail":1,"stat.pickup.minecraft.arrow":91,"stat.pickup.minecraft.iron_sword":4,"stat.useItem.minecraft.sponge":7,"stat.pickup.minecraft.detector_rail":2,"stat.useItem.minecraft.clay":46,"stat.drop.minecraft.banner":1,"stat.useItem.minecraft.packed_ice":5,"stat.drop.minecraft.iron_pickaxe":1,"stat.craftItem.minecraft.iron_hoe":1,"stat.pickup.minecraft.cooked_chicken":5,"stat.fallOneCm":422177,"stat.drop.minecraft.stone":12,"stat.drop.minecraft.dye":6,"stat.pickup.minecraft.carrot":16,"stat.pickup.minecraft.melon_seeds":22,"stat.crouchOneCm":120187,"stat.pickup.minecraft.rail":111,"stat.mineBlock.minecraft.chest":11,"stat.drop.minecraft.gold_ore":4,"stat.craftItem.minecraft.iron_ingot":250,"stat.craftItem.minecraft.chest":23,"stat.pickup.minecraft.painting":5,"stat.pickup.minecraft.melon":133,"stat.mineBlock.minecraft.concrete_powder":1,"stat.useItem.minecraft.iron_hoe":36,"stat.craftItem.minecraft.hopper":10,"stat.craftingTableInteraction":231,"stat.dropperInspected":124,"stat.useItem.minecraft.light_blue_shulker_box":15,"stat.pickup.minecraft.comparator":2,"stat.pickup.minecraft.repeater":5,"stat.mineBlock.minecraft.log2":62,"stat.pickup.minecraft.wooden_pickaxe":2,"stat.useItem.minecraft.golden_rail":148,"stat.pickup.minecraft.feather":46,"stat.drop.minecraft.iron_leggings":3,"stat.drop.minecraft.bone":18,"stat.craftItem.minecraft.wooden_button":1,"stat.useItem.minecraft.reeds":142,"stat.useItem.minecraft.furnace":17,"stat.drop.minecraft.concrete":2,"stat.pickup.minecraft.dye":469,"stat.pickup.minecraft.planks":988,"stat.pickup.minecraft.iron_leggings":2,"stat.drop.minecraft.minecart":1,"stat.craftItem.minecraft.diamond_shovel":1,"stat.pickup.minecraft.wheat_seeds":196,"stat.pickup.minecraft.lead":15,"stat.mineBlock.minecraft.gravel":155,"stat.useItem.minecraft.stone_pickaxe":140,"stat.breakItem.minecraft.stone_axe":3,"stat.mineBlock.minecraft.glass":1,"stat.useItem.minecraft.enchanting_table":3,"stat.useItem.minecraft.stone_sword":26,"stat.craftItem.minecraft.iron_leggings":3,"stat.drop.minecraft.diamond_hoe":2,"stat.killEntity.Rabbit":2,"stat.useItem.minecraft.wool":53,"stat.craftItem.minecraft.oak_stairs":708,"stat.mineBlock.minecraft.dirt":708,"stat.drop.minecraft.reeds":1,"stat.drop.minecraft.stick":30,"stat.flowerPotted":13,"stat.useItem.minecraft.iron_bars":1,"stat.mineBlock.minecraft.quartz_stairs":1,"stat.drop.minecraft.paper":1,"stat.useItem.minecraft.bread":1,"stat.useItem.minecraft.torch":260,"stat.pickup.minecraft.golden_apple":4,"stat.drop.minecraft.light_blue_shulker_box":1,"stat.drop.minecraft.rotten_flesh":29,"stat.drop.minecraft.porkchop":7,"stat.useItem.minecraft.log":1350,"stat.pickup.minecraft.crafting_table":13,"stat.pickup.minecraft.light_blue_shulker_box":15,"stat.useItem.minecraft.comparator":61,"stat.useItem.minecraft.cobblestone":283,"stat.craftItem.minecraft.crafting_table":16,"stat.useItem.minecraft.gravel":7,"stat.mineBlock.minecraft.double_plant":36,"stat.craftItem.minecraft.boat":1,"stat.minecartOneCm":19682,"stat.pickup.minecraft.redstone_block":1,"stat.pickup.minecraft.log":3437,"stat.drop.minecraft.sign":3,"stat.drop.minecraft.glass_pane":9,"stat.pickup.minecraft.iron_pickaxe":1,"stat.drop.minecraft.iron_ore":46,"stat.craftItem.minecraft.gold_ingot":16,"stat.drop.minecraft.planks":88,"stat.pickup.minecraft.hopper":12,"stat.drop.minecraft.sapling":4,"stat.pickup.minecraft.chicken":27,"stat.pickup.minecraft.tipped_arrow":1,"stat.pickup.minecraft.sapling":408,"stat.pickup.minecraft.wooden_door":7,"stat.pickup.minecraft.apple":47,"stat.useItem.minecraft.fireworks":1,"stat.useItem.minecraft.glass_pane":155,"stat.pickup.minecraft.banner":3,"stat.useItem.minecraft.birch_door":4,"stat.drop.minecraft.bow":1,"stat.pickup.minecraft.beetroot":3,"stat.craftItem.minecraft.bucket":2,"stat.useItem.minecraft.iron_sword":358,"stat.craftItem.minecraft.planks":6058,"stat.useItem.minecraft.barrier":7,"stat.itemEnchanted":4,"stat.useItem.minecraft.wooden_pressure_plate":4,"stat.useItem.minecraft.stonebrick":191,"stat.mineBlock.minecraft.log":3749,"stat.craftItem.minecraft.wooden_door":9,"stat.craftItem.minecraft.cooked_chicken":27,"stat.useItem.minecraft.wooden_door":10,"stat.craftItem.minecraft.flower_pot":8,"stat.drop.minecraft.birch_door":3,"stat.useItem.minecraft.spruce_door":7,"stat.craftItem.minecraft.sugar":4,"stat.pickup.minecraft.iron_door":5,"stat.craftItem.minecraft.paper":96,"stat.pickup.minecraft.red_flower":226,"stat.sneakTime":45322,"stat.pickup.minecraft.wool":105,"stat.drop.minecraft.sea_lantern":1,"stat.drop.minecraft.bucket":4,"stat.useItem.minecraft.wooden_axe":19,"stat.drop.minecraft.yellow_flower":2,"stat.useItem.minecraft.brewing_stand":4,"stat.pickup.minecraft.stone_slab":1,"stat.pickup.minecraft.yellow_flower":27,"stat.drop.minecraft.grass":2,"stat.pickup.minecraft.golden_rail":2,"stat.drop.minecraft.wooden_axe":1,"stat.pickup.minecraft.chest":14,"stat.craftItem.minecraft.enchanting_table":1,"stat.drop.minecraft.stone_pickaxe":1,"stat.pickup.minecraft.bone":100,"stat.pickup.minecraft.redstone_torch":2,"stat.pickup.minecraft.stone_pressure_plate":3,"stat.horseOneCm":854535,"stat.pickup.minecraft.lit_pumpkin":4,"stat.useItem.minecraft.iron_axe":2478,"stat.useItem.minecraft.repeater":628,"stat.drop.minecraft.stone_shovel":1,"stat.mineBlock.minecraft.cobblestone":27,"stat.mineBlock.minecraft.pumpkin":4,"stat.useItem.minecraft.beacon":2,"stat.pickup.minecraft.flint":2,"stat.mineBlock.minecraft.yellow_flower":21,"stat.useItem.minecraft.skull":1,"stat.mineBlock.minecraft.brown_mushroom":8,"stat.mineBlock.minecraft.concrete":115,"stat.pickup.minecraft.flower_pot":4,"stat.useItem.minecraft.diamond_sword":8,"stat.swimOneCm":219342,"stat.drop.minecraft.saddle":2,"stat.useItem.minecraft.concrete_powder":81,"stat.climbOneCm":25248,"stat.drop.minecraft.sticky_piston":1,"stat.drop.minecraft.cobblestone":210,"stat.pickup.minecraft.cooked_porkchop":6,"stat.breakItem.minecraft.iron_pickaxe":1,"stat.useItem.minecraft.obsidian":142,"stat.pickup.minecraft.sticky_piston":1,"stat.useItem.minecraft.redstone_torch":378,"stat.useItem.minecraft.dirt":3042,"stat.craftItem.minecraft.purple_shulker_box":1,"stat.pickup.minecraft.bow":7,"stat.pickup.minecraft.iron_boots":3,"stat.drop.minecraft.brick":2,"stat.craftItem.minecraft.furnace":10,"stat.pickup.minecraft.enchanting_table":1,"stat.craftItem.minecraft.iron_boots":4,"stat.useItem.minecraft.detector_rail":5,"stat.craftItem.minecraft.trapdoor":62,"stat.drop.minecraft.ender_pearl":2,"stat.craftItem.minecraft.stone_pickaxe":2,"stat.craftItem.minecraft.cooked_beef":26,"stat.mineBlock.minecraft.obsidian":6,"stat.pickup.minecraft.cobblestone":651,"stat.pickup.minecraft.quartz_stairs":3,"stat.pickup.minecraft.iron_trapdoor":17,"stat.mineBlock.minecraft.carpet":1,"stat.drop.minecraft.fence":6,"stat.pickup.minecraft.diamond_hoe":2,"stat.mineBlock.minecraft.clay":65,"stat.useItem.minecraft.stone_shovel":61,"stat.flyOneCm":12093097,"stat.drop.minecraft.iron_helmet":2,"stat.craftItem.minecraft.glass_bottle":18,"stat.pickup.minecraft.sandstone":2,"stat.drop.minecraft.wheat_seeds":10,"stat.craftItem.minecraft.wooden_slab":42,"stat.useItem.minecraft.cooked_beef":48,"stat.pickup.minecraft.cactus":113,"stat.drop.minecraft.clay_ball":16,"stat.pickup.minecraft.redstone":940,"stat.mineBlock.minecraft.iron_ore":452,"stat.craftItem.minecraft.book":30,"stat.timeSinceDeath":476270,"stat.useItem.minecraft.sign":73,"stat.drop.minecraft.log":90,"stat.cauldronFilled":18,"stat.useItem.minecraft.wooden_slab":112,"stat.drop.minecraft.spider_eye":10,"stat.pickup.minecraft.mutton":71,"stat.useItem.minecraft.iron_door":9,"stat.drop.minecraft.repeater":1,"stat.craftItem.minecraft.iron_block":3,"stat.useItem.minecraft.noteblock":773,"stat.drop.minecraft.activator_rail":1,"stat.drop.minecraft.coal":78,"stat.useItem.minecraft.lever":20,"stat.useItem.minecraft.potato":1,"stat.pickup.minecraft.wooden_axe":1,"stat.pickup.minecraft.dark_oak_door":6,"stat.mineBlock.minecraft.enchanting_table":1,"stat.pickup.minecraft.redstone_lamp":1,"stat.killEntity.Wolf":1,"stat.craftItem.minecraft.concrete_powder":80,"stat.drop.minecraft.dirt":246,"stat.useItem.minecraft.cooked_porkchop":28,"stat.pickup.minecraft.carpet":7,"stat.pickup.minecraft.trapdoor":40,"stat.pickup.minecraft.diamond_shovel":2,"stat.drop.minecraft.beetroot_seeds":7,"stat.drop.minecraft.wool":15,"stat.mineBlock.minecraft.coal_ore":929,"stat.useItem.minecraft.armor_stand":20,"stat.killEntity.Creeper":16,"stat.pickup.minecraft.shield":3,"stat.talkedToVillager":5,"stat.drop.minecraft.spawn_egg":2,"stat.pickup.minecraft.string":65,"stat.drop.minecraft.log2":4,"stat.craftItem.minecraft.brick_block":16,"stat.useItem.minecraft.sea_lantern":281,"stat.entityKilledBy.Skeleton":4,"stat.drop.minecraft.obsidian":1,"stat.drop.minecraft.oak_stairs":3,"stat.useItem.minecraft.dropper":95,"stat.killEntity.Squid":30,"stat.craftItem.minecraft.chest_minecart":1,"stat.sprintOneCm":2788769,"stat.useItem.minecraft.diamond_shovel":1090,"stat.drop.minecraft.leather":11,"stat.craftItem.minecraft.wooden_axe":5,"stat.craftItem.minecraft.stick":108,"stat.drop.minecraft.potion":1,"stat.useItem.minecraft.stone_slab":166,"stat.useItem.minecraft.bed":9,"stat.craftItem.minecraft.gold_nugget":9,"stat.mineBlock.minecraft.diamond_ore":24,"stat.pickup.minecraft.fireworks":7,"stat.pickup.minecraft.grass":5,"stat.mineBlock.minecraft.crafting_table":14,"stat.useItem.minecraft.stone_pressure_plate":15,"stat.useItem.minecraft.diamond_pickaxe":1629,"stat.useItem.minecraft.carrot":1,"stat.useItem.minecraft.bucket":104,"stat.entityKilledBy.Creeper":4,"stat.pickup.minecraft.spawn_egg":1,"stat.mineBlock.minecraft.planks":508,"stat.drop":576,"stat.useItem.minecraft.cake":1,"stat.pickup.minecraft.stone_button":2,"stat.useItem.minecraft.banner":25,"stat.killEntity.Sheep":64,"stat.drop.minecraft.iron_boots":3,"stat.craftItem.minecraft.diamond_pickaxe":1,"stat.useItem.minecraft.cyan_shulker_box":39,"stat.useItem.minecraft.melon_seeds":5,"stat.killEntity.Zombie":63,"stat.craftItem.minecraft.dye":123,"stat.mineBlock.minecraft.gold_ore":70,"stat.diveOneCm":362782,"stat.drop.minecraft.diamond_pickaxe":3,"stat.pickup.minecraft.wheat":23,"stat.mineBlock.minecraft.mossy_cobblestone":1,"stat.craftItem.minecraft.piston":5,"stat.useItem.minecraft.sticky_piston":448,"stat.useItem.minecraft.record_wait":1,"stat.pickup.minecraft.sign":4,"stat.useItem.minecraft.quartz_stairs":306,"stat.drop.minecraft.wooden_pickaxe":3,"stat.pickup.minecraft.gravel":172,"stat.craftItem.minecraft.cooked_porkchop":48,"stat.drop.minecraft.cooked_beef":146,"stat.useItem.minecraft.glass_bottle":22,"stat.killEntity.Slime":2,"stat.useItem.minecraft.diamond_axe":2998,"stat.pickup.minecraft.stone_axe":1,"stat.pickup.minecraft.purple_shulker_box":5,"stat.mineBlock.minecraft.deadbush":38,"stat.pickup.minecraft.obsidian":31,"stat.useItem.minecraft.tnt_minecart":66,"stat.useItem.minecraft.porkchop":2,"stat.useItem.minecraft.carpet":175,"stat.useItem.minecraft.potion":29,"stat.useItem.minecraft.rotten_flesh":12,"stat.drop.minecraft.apple":7,"stat.drop.minecraft.cooked_porkchop":26,"stat.pickup.minecraft.diamond_sword":1,"stat.pickup.minecraft.brick":2,"stat.useItem.minecraft.flower_pot":18,"stat.useItem.minecraft.bedrock":3,"stat.jump":23027,"stat.useItem.minecraft.sand":78,"stat.useItem.minecraft.iron_trapdoor":52,"stat.pickup.minecraft.fence":15,"stat.pickup.minecraft.coal":1131,"stat.pickup.minecraft.iron_helmet":2,"stat.pickup.minecraft.iron_ingot":56,"stat.useItem.minecraft.stone_axe":337,"stat.useItem.minecraft.piston":69,"stat.pickup.minecraft.gunpowder":81,"stat.craftItem.minecraft.bread":1,"stat.pickup.minecraft.spider_eye":17,"stat.craftItem.minecraft.torch":168,"stat.pickup.minecraft.dirt":1022,"stat.useItem.minecraft.stone_button":140,"stat.craftItem.minecraft.iron_helmet":2,"stat.craftItem.minecraft.fermented_spider_eye":3,"stat.drop.minecraft.bed":6,"stat.useItem.minecraft.cooked_chicken":14,"stat.pickup.minecraft.iron_ore":425,"stat.useItem.minecraft.glass":434,"stat.useItem.minecraft.dispenser":38,"stat.pickup.minecraft.stone_shovel":2,"stat.boatOneCm":308962,"stat.pickup.minecraft.gold_ore":134,"stat.useItem.minecraft.sapling":253,"stat.mineBlock.minecraft.lapis_ore":25,"stat.useItem.minecraft.redstone_lamp":23,"stat.mineBlock.minecraft.glass_pane":3,"stat.mineBlock.minecraft.leaves2":4,"stat.brewingstandInteraction":184,"stat.damageTaken":80766,"stat.pickup.minecraft.leather":44,"stat.useItem.minecraft.stone_brick_stairs":9,"stat.mineBlock.minecraft.melon_block":16,"stat.mineBlock.minecraft.red_flower":233,"stat.mineBlock.minecraft.torch":26,"stat.mineBlock.minecraft.furnace":4,"stat.useItem.minecraft.gold_block":54,"stat.dispenserInspected":39,"stat.useItem.minecraft.wooden_pickaxe":91,"stat.drop.minecraft.water_bucket":2,"stat.mineBlock.minecraft.sapling":16,"stat.noteblockTuned":7263,"stat.pickup.minecraft.log2":54,"stat.useItem.minecraft.slime":65,"stat.useItem.minecraft.purple_shulker_box":4,"stat.entityKilledBy.ZombieVillager":1,"stat.pickup.minecraft.prismarine_crystals":22,"stat.pickup.minecraft.reeds":436,"stat.pickup.minecraft.bed":8,"stat.cauldronUsed":13,"stat.pickup.minecraft.concrete":117,"stat.pickup.minecraft.quartz_block":1,"stat.pickup.minecraft.potato":18,"stat.pickup.minecraft.oak_stairs":152,"stat.pickup.minecraft.diamond_axe":3,"stat.entityKilledBy.Zombie":1,"stat.damageDealt":67115,"stat.craftItem.minecraft.glass":98,"stat.drop.minecraft.cooked_chicken":8,"stat.sleepInBed":12,"stat.craftItem.minecraft.anvil":1,"stat.killEntity.Cow":21,"stat.pickup.minecraft.minecart":2,"stat.useItem.minecraft.crafting_table":27,"stat.killEntity.Pig":36,"stat.useItem.minecraft.command_block":8,"stat.craftItem.minecraft.stone_shovel":1,"stat.walkOneCm":13660222,"stat.animalsBred":18,"stat.useItem.minecraft.chest":45,"stat.playerKills":38,"stat.drop.minecraft.wheat":13,"stat.pickup.minecraft.stick":66,"stat.pickup.minecraft.diamond_pickaxe":4,"stat.useItem.minecraft.pumpkin":10,"stat.useItem.minecraft.observer":26,"stat.pickup.minecraft.noteblock":2,"stat.pickup.minecraft.clay_ball":252,"stat.useItem.minecraft.lava_bucket":12,"stat.breakItem.minecraft.stone_pickaxe":1,"stat.drop.minecraft.diamond_axe":2,"stat.useItem.minecraft.redstone_block":79,"stat.useItem.minecraft.item_frame":14,"stat.drop.minecraft.iron_chestplate":4,"stat.shulkerBoxOpened":87,"stat.useItem.minecraft.spruce_stairs":25,"stat.pickup.minecraft.stone":234,"stat.craftItem.minecraft.iron_chestplate":4,"stat.useItem.minecraft.stained_hardened_clay":800,"stat.pickup.minecraft.ender_pearl":4,"stat.useItem.minecraft.leaves":25,"stat.drop.minecraft.wooden_slab":3,"stat.craftItem.minecraft.minecart":2,"stat.pickup.minecraft.cooked_beef":1,"stat.pickup.minecraft.ladder":1,"stat.useItem.minecraft.concrete":168,"stat.useItem.minecraft.netherrack":14,"stat.killEntity.Stray":1,"stat.drop.minecraft.lit_pumpkin":2,"stat.pickup.minecraft.gold_ingot":26,"stat.useItem.minecraft.prismarine":219,"stat.killEntity.Skeleton":59,"stat.craftItem.minecraft.bookshelf":15,"stat.mineBlock.minecraft.cactus":58,"stat.useItem.minecraft.tripwire_hook":24,"stat.killEntity.Chicken":27,"stat.mineBlock.minecraft.redstone_torch":1,"stat.drop.minecraft.crafting_table":1,"stat.useItem.minecraft.iron_block":4,"stat.killEntity.Spider":29,"stat.pickup.minecraft.bread":1,"stat.pickup.minecraft.concrete_powder":1,"stat.mineBlock.minecraft.glowstone":1,"stat.mobKills":397,"stat.killEntity.Mule":1,"stat.craftItem.minecraft.fence":63,"stat.entityKilledBy.Husk":1,"stat.useItem.minecraft.golden_apple":10,"stat.useItem.minecraft.boat":1,"stat.pickup.minecraft.water_bucket":5,"stat.breakItem.minecraft.iron_axe":8,"stat.pickup.minecraft.diamond":85,"stat.pickup.minecraft.beetroot_seeds":27,"stat.pickup.minecraft.iron_horse_armor":5,"stat.mineBlock.minecraft.leaves":344,"stat.useItem.minecraft.hopper_minecart":14,"stat.pickup.minecraft.torch":80,"stat.mineBlock.minecraft.redstone_ore":102,"stat.drop.minecraft.diamond_shovel":1,"stat.drop.minecraft.stone_axe":1,"stat.drop.minecraft.beef":15,"stat.drop.minecraft.arrow":4,"stat.useItem.minecraft.map":4,"stat.craftItem.minecraft.brick":199,"stat.mineBlock.minecraft.stone":704}