{"SURVIVAL":{"armorContents":{"0":{"==":"org.bukkit.inventory.ItemStack","type":"DIAMOND_BOOTS","damage":194},"1":{"==":"org.bukkit.inventory.ItemStack","type":"DIAMOND_LEGGINGS","damage":189},"2":{"==":"org.bukkit.inventory.ItemStack","type":"DIAMOND_CHESTPLATE","damage":194},"3":{"==":"org.bukkit.inventory.ItemStack","type":"DIAMOND_HELMET","damage":194}},"offHandItem":{"==":"org.bukkit.inventory.ItemStack","type":"SHIELD","damage":81},"potions":[],"enderChestContents":{},"inventoryContents":{"26":{"==":"org.bukkit.inventory.ItemStack","type":"ARROW","amount":64},"10":{"==":"org.bukkit.inventory.ItemStack","type":"RAW_BEEF","amount":2},"33":{"==":"org.bukkit.inventory.ItemStack","type":"IRON_SWORD","damage":12},"13":{"==":"org.bukkit.inventory.ItemStack","type":"DIAMOND","amount":11},"35":{"==":"org.bukkit.inventory.ItemStack","type":"IRON_AXE","damage":101},"36":{"==":"org.bukkit.inventory.ItemStack","type":"DIAMOND_BOOTS","damage":194},"37":{"==":"org.bukkit.inventory.ItemStack","type":"DIAMOND_LEGGINGS","damage":189},"38":{"==":"org.bukkit.inventory.ItemStack","type":"DIAMOND_CHESTPLATE","damage":194},"39":{"==":"org.bukkit.inventory.ItemStack","type":"DIAMOND_HELMET","damage":194},"0":{"==":"org.bukkit.inventory.ItemStack","type":"BOW"},"1":{"==":"org.bukkit.inventory.ItemStack","type":"DIAMOND_AXE","damage":226},"2":{"==":"org.bukkit.inventory.ItemStack","type":"TORCH","amount":46},"3":{"==":"org.bukkit.inventory.ItemStack","type":"COOKED_BEEF","amount":22},"4":{"==":"org.bukkit.inventory.ItemStack","type":"GOLDEN_APPLE"},"5":{"==":"org.bukkit.inventory.ItemStack","type":"DIAMOND_SWORD","damage":10},"6":{"==":"org.bukkit.inventory.ItemStack","type":"DIAMOND_PICKAXE","damage":171},"7":{"==":"org.bukkit.inventory.ItemStack","type":"TOTEM"},"8":{"==":"org.bukkit.inventory.ItemStack","type":"SULPHUR"},"9":{"==":"org.bukkit.inventory.ItemStack","type":"LEATHER"},"40":{"==":"org.bukkit.inventory.ItemStack","type":"SHIELD","damage":81},"20":{"==":"org.bukkit.inventory.ItemStack","type":"IRON_PICKAXE","damage":70}},"stats":{"ex":"8.436998","ma":"300","fl":"20","el":"13","xp":"0.8181818","hp":"12.171472549438477","txp":"274","fd":"0.0","ft":"-20","sa":"9.8","ra":"300"}}}